cndx/__init__.py
cndx/main.py
cndx-0.1.0.dist-info/METADATA
cndx-0.1.0.dist-info/WHEEL
cndx-0.1.0.dist-info/entry_points.txt
cndx-0.1.0.dist-info/top_level.txt
cndx-0.1.0.dist-info/RECORD
