Metadata-Version: 2.4
Name: cndx
Version: 0.1.0
Summary: Minimal CLI wrapper for 'conda project run'
Author-email: Kyle Kelley <rgbkrk@gmail.com>
License: MIT
Classifier: Programming Language :: Python :: 3
Classifier: License :: OSI Approved :: MIT License
Classifier: Operating System :: OS Independent
Requires-Python: >=3.7
